motimer/__init__.py
motimer/widget.py
motimer-0.1.2.dist-info/licenses/LICENSE
motimer-0.1.2.dist-info/METADATA
motimer-0.1.2.dist-info/WHEEL
motimer-0.1.2.dist-info/top_level.txt
motimer-0.1.2.dist-info/RECORD
