Metadata-Version: 2.4
Name: motimer
Version: 0.1.2
Summary: A timer and stopwatch widget for marimo notebooks
Author: Sam Parmar
License-Expression: MIT
Project-URL: Homepage, https://github.com/parmsam/motimer
Project-URL: Repository, https://github.com/parmsam/motimer
Project-URL: Issues, https://github.com/parmsam/motimer/issues
Classifier: Operating System :: OS Independent
Classifier: Intended Audience :: Developers
Classifier: Programming Language :: Python :: 3
Classifier: Programming Language :: Python :: 3.8
Classifier: Programming Language :: Python :: 3.9
Classifier: Programming Language :: Python :: 3.10
Classifier: Programming Language :: Python :: 3.11
Requires-Python: >=3.8
License-File: LICENSE
Requires-Dist: anywidget
Requires-Dist: traitlets
Dynamic: license-file
